hog_bisect/__init__.py
hog_bisect/bisect.py
hog_bisect/origin_method.py
hog_bisect/outlier_detection_method.py
hog_bisect/outlier_result_type.py
hog_bisect/utils.py
hidden_outlier_generation-1.0.0.dist-info/LICENSE
hidden_outlier_generation-1.0.0.dist-info/METADATA
hidden_outlier_generation-1.0.0.dist-info/WHEEL
hidden_outlier_generation-1.0.0.dist-info/top_level.txt
hidden_outlier_generation-1.0.0.dist-info/RECORD
