Metadata-Version: 2.1
Name: hidden-outlier-generation
Version: 1.0.0
Summary: Python implementation of the bisect algorithm for hidden outlier generation.
Author-email: David Schulmeister <david.schulmeister@student.kit.edu>
License: The MIT License (MIT)
Project-URL: Homepage, https://github.com/dschulmeist/hidden-outlier-generation
Keywords: hidden,bisect,outlier,generation
Classifier: License :: OSI Approved :: MIT License
Classifier: Programming Language :: Python
Classifier: Programming Language :: Python :: 3
Requires-Python: >=3.8
License-File: LICENSE
Requires-Dist: numpy >=1.21.2
Requires-Dist: pyod >=0.9.4
Requires-Dist: scikit-learn >=1.2.0
Requires-Dist: tensorflow >=2.9.0
Requires-Dist: joblib >=1.3.0
